stdqt/__init__.py
stdqt/_all.py
stdqt/gen.py
stdqt-0.0.2.dist-info/licenses/LICENSE
stdqt-0.0.2.dist-info/METADATA
stdqt-0.0.2.dist-info/WHEEL
stdqt-0.0.2.dist-info/top_level.txt
stdqt-0.0.2.dist-info/RECORD
