Metadata-Version: 2.4
Name: stdqt
Version: 0.0.2
Summary: Include almost all modules and classes of PyQt5.
Home-page: https://github.com/MnlSmile/stdqt
Author: MnlSmile
Author-email: kedoukedou33@163.com
License-File: LICENSE
Requires-Dist: pyqt5
Requires-Dist: PyQtWebEngine
Dynamic: author
Dynamic: author-email
Dynamic: home-page
Dynamic: license-file
Dynamic: requires-dist
Dynamic: summary
